erpbrasil.assinatura-1.7.0-py3.7-nspkg.pth
erpbrasil/assinatura/__init__.py
erpbrasil/assinatura/__main__.py
erpbrasil/assinatura/assinatura.py
erpbrasil/assinatura/certificado.py
erpbrasil/assinatura/cli.py
erpbrasil/assinatura/excecoes.py
erpbrasil/assinatura/misc.py
erpbrasil.assinatura-1.7.0.dist-info/AUTHORS.rst
erpbrasil.assinatura-1.7.0.dist-info/LICENSE
erpbrasil.assinatura-1.7.0.dist-info/METADATA
erpbrasil.assinatura-1.7.0.dist-info/WHEEL
erpbrasil.assinatura-1.7.0.dist-info/entry_points.txt
erpbrasil.assinatura-1.7.0.dist-info/namespace_packages.txt
erpbrasil.assinatura-1.7.0.dist-info/top_level.txt
erpbrasil.assinatura-1.7.0.dist-info/RECORD
